napari_potential_field_navigation/__init__.py
napari_potential_field_navigation/_reader.py
napari_potential_field_navigation/_sample_data.py
napari_potential_field_navigation/_scratch.py
napari_potential_field_navigation/_test_plugin.py
napari_potential_field_navigation/_version.py
napari_potential_field_navigation/_widget.py
napari_potential_field_navigation/_writer.py
napari_potential_field_navigation/fields.py
napari_potential_field_navigation/geometries.py
napari_potential_field_navigation/napari.yaml
napari_potential_field_navigation/simulations.py
napari_potential_field_navigation/_tests/__init__.py
napari_potential_field_navigation/_tests/test_sample_data.py
napari_potential_field_navigation/_tests/test_widget.py
napari_potential_field_navigation-0.1.1.dist-info/LICENSE
napari_potential_field_navigation-0.1.1.dist-info/METADATA
napari_potential_field_navigation-0.1.1.dist-info/WHEEL
napari_potential_field_navigation-0.1.1.dist-info/entry_points.txt
napari_potential_field_navigation-0.1.1.dist-info/top_level.txt
napari_potential_field_navigation-0.1.1.dist-info/RECORD
