Metadata-Version: 2.1
Name: napari-potential-field-navigation
Version: 0.1.1
Summary: A simple plugin for trajectories visualisations in napari for lung navigation in CTs scans
Home-page: https://github.com/rcremese/napari-potential-field-navigation
Author: Robin CREMESE
Author-email: robin.cremese@gmail.com
License: MPL-2.0
Project-URL: Bug Tracker, https://github.com/rcremese/napari-potential-field-navigation/issues
Project-URL: Documentation, https://github.com/rcremese/napari-potential-field-navigation#README.md
Project-URL: Source Code, https://github.com/rcremese/napari-potential-field-navigation
Project-URL: User Support, https://github.com/rcremese/napari-potential-field-navigation/issues
Classifier: Development Status :: 2 - Pre-Alpha
Classifier: Framework :: napari
Classifier: Intended Audience :: Developers
Classifier: License :: OSI Approved :: Mozilla Public License 2.0 (MPL 2.0)
Classifier: Operating System :: OS Independent
Classifier: Programming Language :: Python
Classifier: Programming Language :: Python :: 3
Classifier: Programming Language :: Python :: 3 :: Only
Classifier: Programming Language :: Python :: 3.8
Classifier: Programming Language :: Python :: 3.9
Classifier: Programming Language :: Python :: 3.10
Classifier: Topic :: Scientific/Engineering :: Image Processing
Requires-Python: >=3.8
License-File: LICENSE
Requires-Dist: napari
Requires-Dist: numpy
Requires-Dist: magicgui
Requires-Dist: qtpy
Requires-Dist: scikit-image
Requires-Dist: napari-itk-io
Requires-Dist: taichi
Provides-Extra: testing
Requires-Dist: tox ; extra == 'testing'
Requires-Dist: pytest ; extra == 'testing'
Requires-Dist: pytest-cov ; extra == 'testing'
Requires-Dist: pytest-qt ; extra == 'testing'
Requires-Dist: napari ; extra == 'testing'
Requires-Dist: pyqt5 ; extra == 'testing'
